MANIFEST.in
README
distribute_setup.py
setup.py
cvrfparse/__init__.py
cvrfparse/cvrfparse.py
cvrfparse.egg-info/PKG-INFO
cvrfparse.egg-info/SOURCES.txt
cvrfparse.egg-info/dependency_links.txt
cvrfparse.egg-info/entry_points.txt
cvrfparse.egg-info/requires.txt
cvrfparse.egg-info/top_level.txt
cvrfparse/sample-xml/CVRF-1.1-cisco-sa-20110525-rvs4000.xml
cvrfparse/schemata/catalog.xml
cvrfparse/schemata/common/1.1/common.xsd
cvrfparse/schemata/cvrf/1.1/cvrf.xsd
cvrfparse/schemata/dublincore/dc.xsd
cvrfparse/schemata/prod/1.1/prod.xsd
cvrfparse/schemata/scap/cpe-language_2.2a.xsd
cvrfparse/schemata/scap/cvss-v2_0.9.xsd
cvrfparse/schemata/scap/scap-core_0.9.xsd
cvrfparse/schemata/vuln/1.1/vuln.xsd
cvrfparse/schemata/w3.org/xml.xsd