Metadata-Version: 1.0
Name: cvrfparse
Version: 0.10
Summary: CVRF parsing/validation utility
Home-page: http://pypi.python.org/pypi/cvrfparse
Author: Mike Schiffman
Author-email: mschiffm@cisco.com
License: UNKNOWN
Platform: UNKNOWN
